get_sms/__init__.py
getsms-0.1.dist-info/LICENSE
getsms-0.1.dist-info/METADATA
getsms-0.1.dist-info/WHEEL
getsms-0.1.dist-info/top_level.txt
getsms-0.1.dist-info/RECORD
