Metadata-Version: 2.1
Name: getsms
Version: 0.1
Summary: GetSms
Home-page: https://github.com/begyy/getsms
Author: Sadullayev Bekhzod
Author-email: begymrx@gmail.com
License: UNKNOWN
Platform: UNKNOWN
Classifier: Programming Language :: Python :: 3
Classifier: License :: OSI Approved :: MIT License
Classifier: Operating System :: OS Independent
Requires-Python: >=3.5
Requires-Dist: requests
